random_bode_generator/__init__.py
serial_utils-0.5.0.dist-info/METADATA
serial_utils-0.5.0.dist-info/WHEEL
serial_utils-0.5.0.dist-info/top_level.txt
serial_utils-0.5.0.dist-info/RECORD
