Metadata-Version: 2.1
Name: serial-utils
Version: 0.5.0
Summary: package for fascilitating serial communication between python and arduino
Home-page: https://github.com/ryanGT/serial_utils
Author: Ryan Krauss
Author-email: ryanwkrauss@gmail.com
License: UNKNOWN
Platform: UNKNOWN
Classifier: Programming Language :: Python :: 3
Classifier: License :: OSI Approved :: MIT License
Classifier: Operating System :: OS Independent
